{
  "weekly": [
    {
      "weekStart": "2026-06-07T15:00:00.000Z",
      "login": "piyushaneja30",
      "xp": 465,
      "snapshot": {
        "prsMerged": 1,
        "prsOpened": 13,
        "reviews": 91,
        "issuesClosed": 0,
        "issuesOpened": 0,
        "commits": 1,
        "comments": 0
      }
    },
    {
      "weekStart": "2026-05-31T15:00:00.000Z",
      "login": "spookied",
      "xp": 1147.5,
      "snapshot": {
        "prsMerged": 35,
        "prsOpened": 36,
        "reviews": 38,
        "issuesClosed": 21,
        "issuesOpened": 15,
        "commits": 109,
        "comments": 0
      }
    },
    {
      "weekStart": "2026-05-24T15:00:00.000Z",
      "login": "hosshan",
      "xp": 1119,
      "snapshot": {
        "prsMerged": 39,
        "prsOpened": 37,
        "reviews": 17,
        "issuesClosed": 14,
        "issuesOpened": 26,
        "commits": 135,
        "comments": 0
      }
    },
    {
      "weekStart": "2026-05-17T15:00:00.000Z",
      "login": "hosshan",
      "xp": 585,
      "snapshot": {
        "prsMerged": 16,
        "prsOpened": 23,
        "reviews": 18,
        "issuesClosed": 9,
        "issuesOpened": 30,
        "commits": 55,
        "comments": 0
      }
    },
    {
      "weekStart": "2026-05-10T15:00:00.000Z",
      "login": "koolii",
      "xp": 1362,
      "snapshot": {
        "prsMerged": 42,
        "prsOpened": 45,
        "reviews": 40,
        "issuesClosed": 12,
        "issuesOpened": 77,
        "commits": 141,
        "comments": 0
      }
    }
  ],
  "monthly": [
    {
      "month": "2026-05",
      "login": "spookied",
      "xp": 1488,
      "snapshot": {
        "prsMerged": 40,
        "prsOpened": 42,
        "reviews": 44,
        "issuesClosed": 30,
        "issuesOpened": 24,
        "commits": 202,
        "comments": 0
      }
    },
    {
      "month": "2026-04",
      "login": "koolii",
      "xp": 4207.5,
      "snapshot": {
        "prsMerged": 119,
        "prsOpened": 142,
        "reviews": 150,
        "issuesClosed": 28,
        "issuesOpened": 97,
        "commits": 644,
        "comments": 0
      }
    }
  ]
}
