{
  "generatedAt": "2026-07-24T06:46:01.369Z",
  "isoWeek": 30,
  "weekStart": "2026-07-19T15:00:00.000Z",
  "squads": [
    {
      "index": 11,
      "name": "Shadow Monarchs",
      "totalXp": 1515,
      "rank": 1,
      "members": [
        {
          "login": "anshaneja5",
          "weeklyXp": 835.5
        },
        {
          "login": "spookied",
          "weeklyXp": 607.5
        },
        {
          "login": "seipan",
          "weeklyXp": 69
        },
        {
          "login": "ichibe-tani",
          "weeklyXp": 0
        },
        {
          "login": "miya1to9",
          "weeklyXp": 3
        }
      ]
    },
    {
      "index": 6,
      "name": "Neon Samurai Guild",
      "totalXp": 1339.5,
      "rank": 2,
      "members": [
        {
          "login": "koolii",
          "weeklyXp": 982.5
        },
        {
          "login": "simran-261",
          "weeklyXp": 213
        },
        {
          "login": "grvup",
          "weeklyXp": 123
        },
        {
          "login": "YUKI0919-rimo",
          "weeklyXp": 9
        },
        {
          "login": "Mayu-infinite",
          "weeklyXp": 12
        }
      ]
    },
    {
      "index": 8,
      "name": "Steel Lotus Order",
      "totalXp": 1260,
      "rank": 3,
      "members": [
        {
          "login": "harshit1818",
          "weeklyXp": 879
        },
        {
          "login": "prernadabi23",
          "weeklyXp": 40.5
        },
        {
          "login": "Altair-05",
          "weeklyXp": 334.5
        },
        {
          "login": "SoichiroTanakaRimo",
          "weeklyXp": 0
        },
        {
          "login": "Doraemon012",
          "weeklyXp": 6
        }
      ]
    },
    {
      "index": 2,
      "name": "Red Gate Runners",
      "totalXp": 1090.5,
      "rank": 4,
      "members": [
        {
          "login": "yyamada12",
          "weeklyXp": 930
        },
        {
          "login": "NishaMe",
          "weeklyXp": 37.5
        },
        {
          "login": "kamalgurjar7",
          "weeklyXp": 123
        },
        {
          "login": "ryu38",
          "weeklyXp": 0
        },
        {
          "login": "rimo",
          "weeklyXp": 0
        }
      ]
    },
    {
      "index": 12,
      "name": "Iron Fang Corps",
      "totalXp": 864,
      "rank": 5,
      "members": [
        {
          "login": "mosa-rimo",
          "weeklyXp": 153
        },
        {
          "login": "lot-koichi",
          "weeklyXp": 670.5
        },
        {
          "login": "rei-ayanami-00-ai",
          "weeklyXp": 0
        },
        {
          "login": "blues5th",
          "weeklyXp": 24
        },
        {
          "login": "Abhinav232004",
          "weeklyXp": 16.5
        }
      ]
    },
    {
      "index": 5,
      "name": "Ashen Blade Society",
      "totalXp": 805.5,
      "rank": 6,
      "members": [
        {
          "login": "soliste16",
          "weeklyXp": 646.5
        },
        {
          "login": "rimo-asuka-langley",
          "weeklyXp": 99
        },
        {
          "login": "enoki1003",
          "weeklyXp": 48
        },
        {
          "login": "ChahitKolte2112",
          "weeklyXp": 12
        }
      ]
    },
    {
      "index": 3,
      "name": "Crimson Emperor Order",
      "totalXp": 673.5,
      "rank": 7,
      "members": [
        {
          "login": "piyushaneja30",
          "weeklyXp": 297
        },
        {
          "login": "KentoMoriwaki",
          "weeklyXp": 75
        },
        {
          "login": "HrxSrv",
          "weeklyXp": 288
        },
        {
          "login": "kumarpradeepp",
          "weeklyXp": 13.5
        },
        {
          "login": "Soichiro5",
          "weeklyXp": 0
        }
      ]
    },
    {
      "index": 1,
      "name": "Eternal Dark Guild",
      "totalXp": 621,
      "rank": 8,
      "members": [
        {
          "login": "shinji-ikari-01",
          "weeklyXp": 549
        },
        {
          "login": "user-ank",
          "weeklyXp": 27
        },
        {
          "login": "blazethunderstorm",
          "weeklyXp": 16.5
        },
        {
          "login": "Ak-soni2",
          "weeklyXp": 3
        },
        {
          "login": "kanba84",
          "weeklyXp": 25.5
        }
      ]
    },
    {
      "index": 4,
      "name": "Void Walker Corps",
      "totalXp": 613.5,
      "rank": 9,
      "members": [
        {
          "login": "hosshan",
          "weeklyXp": 474
        },
        {
          "login": "adityaghai07",
          "weeklyXp": 51
        },
        {
          "login": "kesharibhai84",
          "weeklyXp": 72
        },
        {
          "login": "kinakonari",
          "weeklyXp": 16.5
        },
        {
          "login": "takahiro-impara",
          "weeklyXp": 0
        }
      ]
    },
    {
      "index": 0,
      "name": "Twilight Hunters",
      "totalXp": 454.5,
      "rank": 10,
      "members": [
        {
          "login": "naoyuki313",
          "weeklyXp": 351
        },
        {
          "login": "Anitesh2004",
          "weeklyXp": 40.5
        },
        {
          "login": "Atharva-Kanherkar",
          "weeklyXp": 10.5
        },
        {
          "login": "kavyaNIS",
          "weeklyXp": 6
        },
        {
          "login": "HaruhiSaito",
          "weeklyXp": 46.5
        }
      ]
    },
    {
      "index": 13,
      "name": "Crimson Gate Hunters",
      "totalXp": 360,
      "rank": 11,
      "members": [
        {
          "login": "una115",
          "weeklyXp": 178.5
        },
        {
          "login": "t-sano-kf",
          "weeklyXp": 181.5
        },
        {
          "login": "alok410kr",
          "weeklyXp": 0
        },
        {
          "login": "kgsi",
          "weeklyXp": 0
        }
      ]
    },
    {
      "index": 7,
      "name": "Obsidian Fang Clan",
      "totalXp": 319.5,
      "rank": 12,
      "members": [
        {
          "login": "awakia",
          "weeklyXp": 241.5
        },
        {
          "login": "Kan0420",
          "weeklyXp": 57
        },
        {
          "login": "Natsukix98",
          "weeklyXp": 0
        },
        {
          "login": "komei2433",
          "weeklyXp": 0
        },
        {
          "login": "26krkz",
          "weeklyXp": 21
        }
      ]
    },
    {
      "index": 9,
      "name": "Dragon Scale Guild",
      "totalXp": 304.5,
      "rank": 13,
      "members": [
        {
          "login": "Dev-the-coder",
          "weeklyXp": 96
        },
        {
          "login": "anujpatel03",
          "weeklyXp": 150
        },
        {
          "login": "wakamsha",
          "weeklyXp": 58.5
        },
        {
          "login": "shivamshaw23",
          "weeklyXp": 0
        }
      ]
    },
    {
      "index": 10,
      "name": "Black Blade Guild",
      "totalXp": 225,
      "rank": 14,
      "members": [
        {
          "login": "takeuchi-haruka",
          "weeklyXp": 72
        },
        {
          "login": "ishitasancheti29",
          "weeklyXp": 153
        },
        {
          "login": "ayushh0311",
          "weeklyXp": 0
        },
        {
          "login": "riiiiiisha",
          "weeklyXp": 0
        }
      ]
    }
  ]
}
